localnet.py
localnet-0.2.0.dist-info/LICENSE
localnet-0.2.0.dist-info/METADATA
localnet-0.2.0.dist-info/WHEEL
localnet-0.2.0.dist-info/entry_points.txt
localnet-0.2.0.dist-info/top_level.txt
localnet-0.2.0.dist-info/RECORD
