Metadata-Version: 2.1
Name: localnet
Version: 0.2.0
Summary: Module and script to check if local machine is on agiven network.
Home-page: https://gitlab.com/ndav/localnet
Author: tty72.com
Author-email: dev@tty72.com
License: GPLv3
Keywords: networking address console interface
Platform: UNKNOWN
Classifier: Development Status :: 5 - Production/Stable
Classifier: Intended Audience :: System Administrators
Classifier: License :: OSI Approved :: GNU General Public License v3 or later (GPLv3+)
Classifier: Operating System :: Unix
Classifier: Operating System :: POSIX
Classifier: Environment :: Console
Classifier: Programming Language :: Python
Classifier: Programming Language :: Python :: 2.7
Classifier: Programming Language :: Python :: 3
Classifier: Programming Language :: Python :: 3.3
Classifier: Programming Language :: Python :: 3.4
Classifier: Programming Language :: Python :: 3.5
Classifier: Programming Language :: Python :: 3.6
Classifier: Programming Language :: Python :: Implementation :: CPython
Classifier: Programming Language :: Python :: Implementation :: PyPy
Classifier: Natural Language :: English
Classifier: Topic :: Utilities
Classifier: Topic :: System :: Networking
Classifier: Topic :: System :: Networking :: Monitoring
